Workbook

Sheet Dashbord
A1: ГИБРИДНЫЙ КОНДОР v2 — ТОРГОВЫЙ ДАШБОРД
A2: SBER | BUY PUT(Ц-10) / SELL PUT(Ц) / BUY CALL(Ц+5) / SELL CALL(Ц+15) + Акции 1000 шт
A3: Зелёный = вводить вручную | Синий = авто-формула | Обновлять ежедневно
A5: ТЕКУЩАЯ ПОЗИЦИЯ | D5: РЫНОЧНЫЕ ДАННЫЕ (вводить каждый день) | G5: СИГНАЛ ПРИНЯТИЯ РЕШЕНИЯ
A6: Дата входа: | D6: Дата: | G6: РЕЖИМ: | H6: =IF(E12="","Введи данные",IF(AND(E12<6,ABS(E13)<3,E14<3),"ФЛЭТ",IF(OR(E12>10,ABS(E13)>6),IF(E13>0,"ТРЕНД ВВЕРХ","ТРЕНД ВНИЗ"),"ЖДАТЬ")))
A7: Цена входа S0: | B7: 317.2 | D7: Close: | E7: =FILTERXML(WEBSERVICE("https://iss.moex.com/iss/engines/stock/markets/shares/boards/TQBR/securities/SBER/candles.xml?from="&TEXT(E16,"yyyy-mm-dd")&"&till="&TEXT(E16,"yyyy-mm-dd")&"&interval=24"),"//row/@close") | G7: ДЕЙСТВИЕ: | H7: =IF(H6="Введи данные","Заполни поля E6:E11",IF(H6="ФЛЭТ","ШАГ1: Продать BUY CALL "&B11&" | ШАГ2: Roll откупить "&B12&" продать ATM | ШАГ3: PUT "&B9,IF(H6="ТРЕНД ВВЕРХ","НЕ трогать CALL. Акции растут. Следить страйк "&B12,IF(H6="ТРЕНД ВНИЗ","НЕ продавать PUT. BUY PUT "&B9&" защищает.",""))))
A8: Центр. страйк (Ц): | B8: 315 | D8: High: | E8: =FILTERXML(WEBSERVICE("https://iss.moex.com/iss/engines/stock/markets/shares/boards/TQBR/securities/SBER/candles.xml?from="&TEXT(E16,"yyyy-mm-dd")&"&till="&TEXT(E16,"yyyy-mm-dd")&"&interval=24"),"//row/@high")
A9: BUY PUT страйк: | B9: 305 | D9: Low: | E9: =FILTERXML(WEBSERVICE("https://iss.moex.com/iss/engines/stock/markets/shares/boards/TQBR/securities/SBER/candles.xml?from="&TEXT(E16,"yyyy-mm-dd")&"&till="&TEXT(E16,"yyyy-mm-dd")&"&interval=24"),"//row/@low") | G9: Фаза 2 активна? | H9: =IF(E15="","нет данных",IF(E15>=10,"ДА: День "&E15&" — проверь журнал флэт-дней","НЕТ: День "&E15&" из 21"))
A10: SELL PUT страйк: | B10: 315 | D10: Вч.Close: | E10: =FILTERXML(WEBSERVICE("https://iss.moex.com/iss/engines/stock/markets/shares/boards/TQBR/securities/SBER/candles.xml?from="&TEXT(E17,"yyyy-mm-dd")&"&till="&TEXT(E17,"yyyy-mm-dd")&"&interval=24"),"//row/@close")
A11: BUY CALL страйк: | B11: 320 | D11: IV%: | E11: =E18 | G11: ЖЁСТКИЕ ЗАПРЕТЫ
A12: SELL CALL страйк: | B12: 330 | D12: R = H-L | E12: =IF(AND(E8<>"",E9<>""),E8-E9,"") | G12: R>12руб→не торговать | После -10руб→нет SELL PUT 2дня | После +10руб→нет Roll 2дня
A13: Акции LONG, шт: | B13: 1000 | D13: Momentum | E13: =IF(AND(E7<>"",E10<>""),E7-E10,"") | G13: Перед/после новостей ЦБ или дивидендов → не активировать Фазу 2
A14: Дата экспирации: | D14: Δ от центра | E14: =IF(AND(E7<>"",B8<>""),ABS(E7-B8),"") | G14: Roll: нет если до экспир.<7 дней или SELL CALL вырос>150% цены входа
A15: Дней до экспир. | B15: =IF(B14="","",MAX(0,B14-TODAY())) | D15: День цикла № | E15: =IF(AND(B6<>"",E6<>""),MAX(1,E6-B6+1),"") | H15: ОБНОВИТЬ: Data -> Refresh All (или Ctrl+Alt+F5)
D16: Торг. дата | E16: =IF(E6<>"",E6,TODAY()-1) | H16: СТАДИЯ СТРАТЕГИИ | I16: =IF(E15<10,"ФАЗА 1: базовый кондор",IF(AND(H6="ФЛЭТ",E15>=10),"ФАЗА 2: продать BUY CALL и Roll CALL","ФАЗА 1/ожидание"))
D17: Пред. торг. дата | E17: =WORKDAY(E16,-1)
D18: IV ATM, % (вручную) | E18: 0.125 | H18: НАЧАЛЬНЫЕ ЦЕНЫ ОПЦИОНОВ | J18: ТЕКУЩИЕ ЦЕНЫ ОПЦИОНОВ | L18: СОСЕДНИЕ СТРАЙКИ
D19: MOEX URL (Close/High/Low) | E19: ="https://iss.moex.com/iss/engines/stock/markets/shares/boards/TQBR/securities/SBER/candles.xml?from="&TEXT(E16,"yyyy-mm-dd")&"&till="&TEXT(E16,"yyyy-mm-dd")&"&interval=24" | L19: PUT ниже | M19: =B9-5
H20: SELL PUT вход | J20: SELL PUT тек. | L20: PUT ATM | M20: =B10
H21: BUY CALL вход | J21: BUY CALL тек. | L21: CALL ATM | M21: =B11
H22: SELL CALL вход | J22: SELL CALL тек. | L22: CALL выше | M22: =B12+5
L23: Введи вручную текущие цены соседних страйков
H24: В Windows Excel: нажми кнопку/макрос Refresh Quotes
H25: Если Excel спросит: Разрешить содержимое / Включить макросы

Sheet Journal
A1: ЕЖЕДНЕВНЫЙ ЖУРНАЛ НАБЛЮДЕНИЙ
A2: Вводи Close/High/Low/PrevClose каждый день — остальное считается автоматически
A3: № | B3: Дата | C3: Close | D3: High | E3: Low | F3: Prev Close | G3: R (H-L) | H3: Moment | I3: Дельта | J3: IV% | K3: РЕЖИМ | L3: CALL? | M3: PUT? | N3: ФАЗА2? | O3: ЗАМЕТКИ
A4: 1 | G4: =IF(AND(D4<>"",E4<>""),D4-E4,"") | H4: =IF(AND(C4<>"",F4<>""),C4-F4,"") | I4: =IF(AND(C4<>"",Dashbord!$B$8<>""),ABS(C4-Dashbord!$B$8),"") | K4: =IF(G4="","",IF(AND(G4<6,ABS(H4)<3,I4<3),"FLAT",IF(OR(G4>10,ABS(H4)>6),IF(H4>0,"TREND UP","TREND DOWN"),"WAIT"))) | L4: =IF(K4="","",IF(K4="FLAT","YES",IF(K4="TREND UP","NO","WAIT"))) | M4: =IF(K4="","",IF(K4="TREND DOWN","NO",IF(K4="FLAT","YES","WAIT"))) | N4: =IF(K4="","",IF(COUNTIF(K4:K4,"FLAT")>=8,"ACTIVATE","No: "&COUNTIF(K4:K4,"FLAT")&"/10"))
A5: 2 | G5: =IF(AND(D5<>"",E5<>""),D5-E5,"") | H5: =IF(AND(C5<>"",F5<>""),C5-F5,"") | I5: =IF(AND(C5<>"",Dashbord!$B$8<>""),ABS(C5-Dashbord!$B$8),"") | K5: =IF(G5="","",IF(AND(G5<6,ABS(H5)<3,I5<3),"FLAT",IF(OR(G5>10,ABS(H5)>6),IF(H5>0,"TREND UP","TREND DOWN"),"WAIT"))) | L5: =IF(K5="","",IF(K5="FLAT","YES",IF(K5="TREND UP","NO","WAIT"))) | M5: =IF(K5="","",IF(K5="TREND DOWN","NO",IF(K5="FLAT","YES","WAIT"))) | N5: =IF(K5="","",IF(COUNTIF(K4:K5,"FLAT")>=8,"ACTIVATE","No: "&COUNTIF(K4:K5,"FLAT")&"/10"))
A6: 3 | G6: =IF(AND(D6<>"",E6<>""),D6-E6,"") | H6: =IF(AND(C6<>"",F6<>""),C6-F6,"") | I6: =IF(AND(C6<>"",Dashbord!$B$8<>""),ABS(C6-Dashbord!$B$8),"") | K6: =IF(G6="","",IF(AND(G6<6,ABS(H6)<3,I6<3),"FLAT",IF(OR(G6>10,ABS(H6)>6),IF(H6>0,"TREND UP","TREND DOWN"),"WAIT"))) | L6: =IF(K6="","",IF(K6="FLAT","YES",IF(K6="TREND UP","NO","WAIT"))) | M6: =IF(K6="","",IF(K6="TREND DOWN","NO",IF(K6="FLAT","YES","WAIT"))) | N6: =IF(K6="","",IF(COUNTIF(K4:K6,"FLAT")>=8,"ACTIVATE","No: "&COUNTIF(K4:K6,"FLAT")&"/10"))
A7: 4 | G7: =IF(AND(D7<>"",E7<>""),D7-E7,"") | H7: =IF(AND(C7<>"",F7<>""),C7-F7,"") | I7: =IF(AND(C7<>"",Dashbord!$B$8<>""),ABS(C7-Dashbord!$B$8),"") | K7: =IF(G7="","",IF(AND(G7<6,ABS(H7)<3,I7<3),"FLAT",IF(OR(G7>10,ABS(H7)>6),IF(H7>0,"TREND UP","TREND DOWN"),"WAIT"))) | L7: =IF(K7="","",IF(K7="FLAT","YES",IF(K7="TREND UP","NO","WAIT"))) | M7: =IF(K7="","",IF(K7="TREND DOWN","NO",IF(K7="FLAT","YES","WAIT"))) | N7: =IF(K7="","",IF(COUNTIF(K4:K7,"FLAT")>=8,"ACTIVATE","No: "&COUNTIF(K4:K7,"FLAT")&"/10"))
A8: 5 | G8: =IF(AND(D8<>"",E8<>""),D8-E8,"") | H8: =IF(AND(C8<>"",F8<>""),C8-F8,"") | I8: =IF(AND(C8<>"",Dashbord!$B$8<>""),ABS(C8-Dashbord!$B$8),"") | K8: =IF(G8="","",IF(AND(G8<6,ABS(H8)<3,I8<3),"FLAT",IF(OR(G8>10,ABS(H8)>6),IF(H8>0,"TREND UP","TREND DOWN"),"WAIT"))) | L8: =IF(K8="","",IF(K8="FLAT","YES",IF(K8="TREND UP","NO","WAIT"))) | M8: =IF(K8="","",IF(K8="TREND DOWN","NO",IF(K8="FLAT","YES","WAIT"))) | N8: =IF(K8="","",IF(COUNTIF(K4:K8,"FLAT")>=8,"ACTIVATE","No: "&COUNTIF(K4:K8,"FLAT")&"/10"))
A9: 6 | G9: =IF(AND(D9<>"",E9<>""),D9-E9,"") | H9: =IF(AND(C9<>"",F9<>""),C9-F9,"") | I9: =IF(AND(C9<>"",Dashbord!$B$8<>""),ABS(C9-Dashbord!$B$8),"") | K9: =IF(G9="","",IF(AND(G9<6,ABS(H9)<3,I9<3),"FLAT",IF(OR(G9>10,ABS(H9)>6),IF(H9>0,"TREND UP","TREND DOWN"),"WAIT"))) | L9: =IF(K9="","",IF(K9="FLAT","YES",IF(K9="TREND UP","NO","WAIT"))) | M9: =IF(K9="","",IF(K9="TREND DOWN","NO",IF(K9="FLAT","YES","WAIT"))) | N9: =IF(K9="","",IF(COUNTIF(K4:K9,"FLAT")>=8,"ACTIVATE","No: "&COUNTIF(K4:K9,"FLAT")&"/10"))
A10: 7 | G10: =IF(AND(D10<>"",E10<>""),D10-E10,"") | H10: =IF(AND(C10<>"",F10<>""),C10-F10,"") | I10: =IF(AND(C10<>"",Dashbord!$B$8<>""),ABS(C10-Dashbord!$B$8),"") | K10: =IF(G10="","",IF(AND(G10<6,ABS(H10)<3,I10<3),"FLAT",IF(OR(G10>10,ABS(H10)>6),IF(H10>0,"TREND UP","TREND DOWN"),"WAIT"))) | L10: =IF(K10="","",IF(K10="FLAT","YES",IF(K10="TREND UP","NO","WAIT"))) | M10: =IF(K10="","",IF(K10="TREND DOWN","NO",IF(K10="FLAT","YES","WAIT"))) | N10: =IF(K10="","",IF(COUNTIF(K4:K10,"FLAT")>=8,"ACTIVATE","No: "&COUNTIF(K4:K10,"FLAT")&"/10"))
A11: 8 | G11: =IF(AND(D11<>"",E11<>""),D11-E11,"") | H11: =IF(AND(C11<>"",F11<>""),C11-F11,"") | I11: =IF(AND(C11<>"",Dashbord!$B$8<>""),ABS(C11-Dashbord!$B$8),"") | K11: =IF(G11="","",IF(AND(G11<6,ABS(H11)<3,I11<3),"FLAT",IF(OR(G11>10,ABS(H11)>6),IF(H11>0,"TREND UP","TREND DOWN"),"WAIT"))) | L11: =IF(K11="","",IF(K11="FLAT","YES",IF(K11="TREND UP","NO","WAIT"))) | M11: =IF(K11="","",IF(K11="TREND DOWN","NO",IF(K11="FLAT","YES","WAIT"))) | N11: =IF(K11="","",IF(COUNTIF(K4:K11,"FLAT")>=8,"ACTIVATE","No: "&COUNTIF(K4:K11,"FLAT")&"/10"))
A12: 9 | G12: =IF(AND(D12<>"",E12<>""),D12-E12,"") | H12: =IF(AND(C12<>"",F12<>""),C12-F12,"") | I12: =IF(AND(C12<>"",Dashbord!$B$8<>""),ABS(C12-Dashbord!$B$8),"") | K12: =IF(G12="","",IF(AND(G12<6,ABS(H12)<3,I12<3),"FLAT",IF(OR(G12>10,ABS(H12)>6),IF(H12>0,"TREND UP","TREND DOWN"),"WAIT"))) | L12: =IF(K12="","",IF(K12="FLAT","YES",IF(K12="TREND UP","NO","WAIT"))) | M12: =IF(K12="","",IF(K12="TREND DOWN","NO",IF(K12="FLAT","YES","WAIT"))) | N12: =IF(K12="","",IF(COUNTIF(K4:K12,"FLAT")>=8,"ACTIVATE","No: "&COUNTIF(K4:K12,"FLAT")&"/10"))
A13: 10 | G13: =IF(AND(D13<>"",E13<>""),D13-E13,"") | H13: =IF(AND(C13<>"",F13<>""),C13-F13,"") | I13: =IF(AND(C13<>"",Dashbord!$B$8<>""),ABS(C13-Dashbord!$B$8),"") | K13: =IF(G13="","",IF(AND(G13<6,ABS(H13)<3,I13<3),"FLAT",IF(OR(G13>10,ABS(H13)>6),IF(H13>0,"TREND UP","TREND DOWN"),"WAIT"))) | L13: =IF(K13="","",IF(K13="FLAT","YES",IF(K13="TREND UP","NO","WAIT"))) | M13: =IF(K13="","",IF(K13="TREND DOWN","NO",IF(K13="FLAT","YES","WAIT"))) | N13: =IF(K13="","",IF(COUNTIF(K4:K13,"FLAT")>=8,"ACTIVATE","No: "&COUNTIF(K4:K13,"FLAT")&"/10"))
A14: 11 | G14: =IF(AND(D14<>"",E14<>""),D14-E14,"") | H14: =IF(AND(C14<>"",F14<>""),C14-F14,"") | I14: =IF(AND(C14<>"",Dashbord!$B$8<>""),ABS(C14-Dashbord!$B$8),"") | K14: =IF(G14="","",IF(AND(G14<6,ABS(H14)<3,I14<3),"FLAT",IF(OR(G14>10,ABS(H14)>6),IF(H14>0,"TREND UP","TREND DOWN"),"WAIT"))) | L14: =IF(K14="","",IF(K14="FLAT","YES",IF(K14="TREND UP","NO","WAIT"))) | M14: =IF(K14="","",IF(K14="TREND DOWN","NO",IF(K14="FLAT","YES","WAIT"))) | N14: =IF(K14="","",IF(COUNTIF(K5:K14,"FLAT")>=8,"ACTIVATE","No: "&COUNTIF(K5:K14,"FLAT")&"/10"))
A15: 12 | G15: =IF(AND(D15<>"",E15<>""),D15-E15,"") | H15: =IF(AND(C15<>"",F15<>""),C15-F15,"") | I15: =IF(AND(C15<>"",Dashbord!$B$8<>""),ABS(C15-Dashbord!$B$8),"") | K15: =IF(G15="","",IF(AND(G15<6,ABS(H15)<3,I15<3),"FLAT",IF(OR(G15>10,ABS(H15)>6),IF(H15>0,"TREND UP","TREND DOWN"),"WAIT"))) | L15: =IF(K15="","",IF(K15="FLAT","YES",IF(K15="TREND UP","NO","WAIT"))) | M15: =IF(K15="","",IF(K15="TREND DOWN","NO",IF(K15="FLAT","YES","WAIT"))) | N15: =IF(K15="","",IF(COUNTIF(K6:K15,"FLAT")>=8,"ACTIVATE","No: "&COUNTIF(K6:K15,"FLAT")&"/10"))
A16: 13 | G16: =IF(AND(D16<>"",E16<>""),D16-E16,"") | H16: =IF(AND(C16<>"",F16<>""),C16-F16,"") | I16: =IF(AND(C16<>"",Dashbord!$B$8<>""),ABS(C16-Dashbord!$B$8),"") | K16: =IF(G16="","",IF(AND(G16<6,ABS(H16)<3,I16<3),"FLAT",IF(OR(G16>10,ABS(H16)>6),IF(H16>0,"TREND UP","TREND DOWN"),"WAIT"))) | L16: =IF(K16="","",IF(K16="FLAT","YES",IF(K16="TREND UP","NO","WAIT"))) | M16: =IF(K16="","",IF(K16="TREND DOWN","NO",IF(K16="FLAT","YES","WAIT"))) | N16: =IF(K16="","",IF(COUNTIF(K7:K16,"FLAT")>=8,"ACTIVATE","No: "&COUNTIF(K7:K16,"FLAT")&"/10"))
A17: 14 | G17: =IF(AND(D17<>"",E17<>""),D17-E17,"") | H17: =IF(AND(C17<>"",F17<>""),C17-F17,"") | I17: =IF(AND(C17<>"",Dashbord!$B$8<>""),ABS(C17-Dashbord!$B$8),"") | K17: =IF(G17="","",IF(AND(G17<6,ABS(H17)<3,I17<3),"FLAT",IF(OR(G17>10,ABS(H17)>6),IF(H17>0,"TREND UP","TREND DOWN"),"WAIT"))) | L17: =IF(K17="","",IF(K17="FLAT","YES",IF(K17="TREND UP","NO","WAIT"))) | M17: =IF(K17="","",IF(K17="TREND DOWN","NO",IF(K17="FLAT","YES","WAIT"))) | N17: =IF(K17="","",IF(COUNTIF(K8:K17,"FLAT")>=8,"ACTIVATE","No: "&COUNTIF(K8:K17,"FLAT")&"/10"))
A18: 15 | G18: =IF(AND(D18<>"",E18<>""),D18-E18,"") | H18: =IF(AND(C18<>"",F18<>""),C18-F18,"") | I18: =IF(AND(C18<>"",Dashbord!$B$8<>""),ABS(C18-Dashbord!$B$8),"") | K18: =IF(G18="","",IF(AND(G18<6,ABS(H18)<3,I18<3),"FLAT",IF(OR(G18>10,ABS(H18)>6),IF(H18>0,"TREND UP","TREND DOWN"),"WAIT"))) | L18: =IF(K18="","",IF(K18="FLAT","YES",IF(K18="TREND UP","NO","WAIT"))) | M18: =IF(K18="","",IF(K18="TREND DOWN","NO",IF(K18="FLAT","YES","WAIT"))) | N18: =IF(K18="","",IF(COUNTIF(K9:K18,"FLAT")>=8,"ACTIVATE","No: "&COUNTIF(K9:K18,"FLAT")&"/10"))
A19: 16 | G19: =IF(AND(D19<>"",E19<>""),D19-E19,"") | H19: =IF(AND(C19<>"",F19<>""),C19-F19,"") | I19: =IF(AND(C19<>"",Dashbord!$B$8<>""),ABS(C19-Dashbord!$B$8),"") | K19: =IF(G19="","",IF(AND(G19<6,ABS(H19)<3,I19<3),"FLAT",IF(OR(G19>10,ABS(H19)>6),IF(H19>0,"TREND UP","TREND DOWN"),"WAIT"))) | L19: =IF(K19="","",IF(K19="FLAT","YES",IF(K19="TREND UP","NO","WAIT"))) | M19: =IF(K19="","",IF(K19="TREND DOWN","NO",IF(K19="FLAT","YES","WAIT"))) | N19: =IF(K19="","",IF(COUNTIF(K10:K19,"FLAT")>=8,"ACTIVATE","No: "&COUNTIF(K10:K19,"FLAT")&"/10"))
A20: 17 | G20: =IF(AND(D20<>"",E20<>""),D20-E20,"") | H20: =IF(AND(C20<>"",F20<>""),C20-F20,"") | I20: =IF(AND(C20<>"",Dashbord!$B$8<>""),ABS(C20-Dashbord!$B$8),"") | K20: =IF(G20="","",IF(AND(G20<6,ABS(H20)<3,I20<3),"FLAT",IF(OR(G20>10,ABS(H20)>6),IF(H20>0,"TREND UP","TREND DOWN"),"WAIT"))) | L20: =IF(K20="","",IF(K20="FLAT","YES",IF(K20="TREND UP","NO","WAIT"))) | M20: =IF(K20="","",IF(K20="TREND DOWN","NO",IF(K20="FLAT","YES","WAIT"))) | N20: =IF(K20="","",IF(COUNTIF(K11:K20,"FLAT")>=8,"ACTIVATE","No: "&COUNTIF(K11:K20,"FLAT")&"/10"))
A21: 18 | G21: =IF(AND(D21<>"",E21<>""),D21-E21,"") | H21: =IF(AND(C21<>"",F21<>""),C21-F21,"") | I21: =IF(AND(C21<>"",Dashbord!$B$8<>""),ABS(C21-Dashbord!$B$8),"") | K21: =IF(G21="","",IF(AND(G21<6,ABS(H21)<3,I21<3),"FLAT",IF(OR(G21>10,ABS(H21)>6),IF(H21>0,"TREND UP","TREND DOWN"),"WAIT"))) | L21: =IF(K21="","",IF(K21="FLAT","YES",IF(K21="TREND UP","NO","WAIT"))) | M21: =IF(K21="","",IF(K21="TREND DOWN","NO",IF(K21="FLAT","YES","WAIT"))) | N21: =IF(K21="","",IF(COUNTIF(K12:K21,"FLAT")>=8,"ACTIVATE","No: "&COUNTIF(K12:K21,"FLAT")&"/10"))
A22: 19 | G22: =IF(AND(D22<>"",E22<>""),D22-E22,"") | H22: =IF(AND(C22<>"",F22<>""),C22-F22,"") | I22: =IF(AND(C22<>"",Dashbord!$B$8<>""),ABS(C22-Dashbord!$B$8),"") | K22: =IF(G22="","",IF(AND(G22<6,ABS(H22)<3,I22<3),"FLAT",IF(OR(G22>10,ABS(H22)>6),IF(H22>0,"TREND UP","TREND DOWN"),"WAIT"))) | L22: =IF(K22="","",IF(K22="FLAT","YES",IF(K22="TREND UP","NO","WAIT"))) | M22: =IF(K22="","",IF(K22="TREND DOWN","NO",IF(K22="FLAT","YES","WAIT"))) | N22: =IF(K22="","",IF(COUNTIF(K13:K22,"FLAT")>=8,"ACTIVATE","No: "&COUNTIF(K13:K22,"FLAT")&"/10"))
A23: 20 | G23: =IF(AND(D23<>"",E23<>""),D23-E23,"") | H23: =IF(AND(C23<>"",F23<>""),C23-F23,"") | I23: =IF(AND(C23<>"",Dashbord!$B$8<>""),ABS(C23-Dashbord!$B$8),"") | K23: =IF(G23="","",IF(AND(G23<6,ABS(H23)<3,I23<3),"FLAT",IF(OR(G23>10,ABS(H23)>6),IF(H23>0,"TREND UP","TREND DOWN"),"WAIT"))) | L23: =IF(K23="","",IF(K23="FLAT","YES",IF(K23="TREND UP","NO","WAIT"))) | M23: =IF(K23="","",IF(K23="TREND DOWN","NO",IF(K23="FLAT","YES","WAIT"))) | N23: =IF(K23="","",IF(COUNTIF(K14:K23,"FLAT")>=8,"ACTIVATE","No: "&COUNTIF(K14:K23,"FLAT")&"/10"))
A24: 21 | G24: =IF(AND(D24<>"",E24<>""),D24-E24,"") | H24: =IF(AND(C24<>"",F24<>""),C24-F24,"") | I24: =IF(AND(C24<>"",Dashbord!$B$8<>""),ABS(C24-Dashbord!$B$8),"") | K24: =IF(G24="","",IF(AND(G24<6,ABS(H24)<3,I24<3),"FLAT",IF(OR(G24>10,ABS(H24)>6),IF(H24>0,"TREND UP","TREND DOWN"),"WAIT"))) | L24: =IF(K24="","",IF(K24="FLAT","YES",IF(K24="TREND UP","NO","WAIT"))) | M24: =IF(K24="","",IF(K24="TREND DOWN","NO",IF(K24="FLAT","YES","WAIT"))) | N24: =IF(K24="","",IF(COUNTIF(K15:K24,"FLAT")>=8,"ACTIVATE","No: "&COUNTIF(K15:K24,"FLAT")&"/10"))
... A63: 60 | G63: =IF(AND(D63<>"",E63<>""),D63-E63,"") | H63: =IF(AND(C63<>"",F63<>""),C63-F63,"") | I63: =IF(AND(C63<>"",Dashbord!$B$8<>""),ABS(C63-Dashbord!$B$8),"") | K63: =IF(G63="","",IF(AND(G63<6,ABS(H63)<3,I63<3),"FLAT",IF(OR(G63>10,ABS(H63)>6),IF(H63>0,"TREND UP","TREND DOWN"),"WAIT"))) | L63: =IF(K63="","",IF(K63="FLAT","YES",IF(K63="TREND UP","NO","WAIT"))) | M63: =IF(K63="","",IF(K63="TREND DOWN","NO",IF(K63="FLAT","YES","WAIT"))) | N63: =IF(K63="","",IF(COUNTIF(K54:K63,"FLAT")>=8,"ACTIVATE","No: "&COUNTIF(K54:K63,"FLAT")&"/10"))

Sheet Calc_PnL
A1: КАЛЬКУЛЯТОР СТРАТЕГИИ + P&L ПРОФИЛЬ
A3: ПАРАМЕТРЫ ПОЗИЦИИ | D3: РАСЧЁТ СТОИМОСТИ НОГ (Black-Scholes) | F3: ТЕОР. ЦЕНА | G3: РУЧНЫЕ РЫНОЧНЫЕ ЦЕНЫ
A4: Цена актива S: | B4: =Dashbord!E7 | G4: BUY PUT вход | I4: BUY PUT тек.
A5: Центральный страйк: | B5: 315 | G5: SELL PUT вход | I5: SELL PUT тек.
A6: BUY PUT страйк (Ц-10): | B6: 305 | G6: BUY CALL вход | I6: BUY CALL тек.
A7: SELL PUT страйк (Ц): | B7: 315 | G7: SELL CALL вход | I7: SELL CALL тек.
A8: BUY CALL страйк (Ц+5): | B8: 320
A9: SELL CALL страйк (Ц+15): | B9: 330 | G9: MTM P&L ног, руб | I9: Прогноз Roll
A10: Волатильность σ (HV21): | B10: =Dashbord!E18 | G10: BUY PUT | H10: =(J4-H4)*$B$13 | I10: Новый CALL strike | J10: =Dashbord!M21
A11: Дней до экспирации T: | B11: 21 | G11: SELL PUT | H11: =(H5-J5)*$B$13 | I11: Цена продажи
A12: Акции LONG, шт: | B12: 1000 | G12: BUY CALL | H12: =(J6-H6)*$B$13 | I12: Цена выкупа старого | J12: =J7
A13: Лот опциона: | B13: 100 | G13: SELL CALL | H13: =(H7-J7)*$B$13 | I13: Добавка P&L | J13: =IF(AND(J11<>"",J12<>""),(J11-J12)*$B$13,"")
G14: Опционы итого | H14: =SUM(H10:H13)
G15: Акции MTM | H15: =(B4-Dashbord!B7)*$B$12
G16: Итог MTM | H16: =H14+H15

Sheet Cycles
A1: ЖУРНАЛ ТОРГОВЫХ ЦИКЛОВ (история + статистика)
A2: Заполнять после закрытия каждого цикла | Кум. P&L и статистика — автоматически
A3: № | B3: Дата входа | C3: S0 | D3: Центр | E3: Страйки BP/SP/BC/SC | F3: HV21 | G3: IV вх. | H3: Флэт дней | I3: Фаза2? | J3: Roll? | K3: P&L Кондор | L3: P&L Фаза2 | M3: P&L Roll | N3: P&L ИТОГО | O3: Кум. P&L | P3: Результат | Q3: Заметки
A4: 1 | B4: 03.04.25 | C4: 317.6 | D4: 320 | E4: 310/320/325/335 | F4: 0.373 | G4: 0.429 | H4: 12 | I4: Да | J4: Да | K4: -7354 | L4: 6247 | M4: 1173 | N4: =IF(K4<>"",K4+IF(L4<>"",L4,0)+IF(M4<>"",M4,0),"") | O4: =IF(N4<>"",N4,"") | P4: =IF(N4="","",IF(N4>0,"PROFIT","LOSS"))
A5: 2 | B5: 03.06.25 | C5: 308.3 | D5: 310 | E5: 300/310/315/325 | F5: 0.239 | G5: 0.275 | H5: 12 | I5: Да | J5: Да | K5: 1661 | L5: 3543 | M5: 2382 | N5: =IF(K5<>"",K5+IF(L5<>"",L5,0)+IF(M5<>"",M5,0),"") | O5: =IF(N5<>"",N5+IF(O4<>"",O4,0),"") | P5: =IF(N5="","",IF(N5>0,"PROFIT","LOSS"))
A6: 3 | B6: 01.07.25 | C6: 310.2 | D6: 310 | E6: 300/310/315/325 | F6: 0.235 | G6: 0.27 | H6: 20 | I6: Да | J6: Да | K6: 734 | L6: 3320 | M6: 5004 | N6: =IF(K6<>"",K6+IF(L6<>"",L6,0)+IF(M6<>"",M6,0),"") | O6: =IF(N6<>"",N6+IF(O5<>"",O5,0),"") | P6: =IF(N6="","",IF(N6>0,"PROFIT","LOSS"))
A7: 4 | B7: 22.07.25 | C7: 310.1 | D7: 310 | E7: 300/310/315/325 | F7: 0.119 | G7: 0.137 | H7: 17 | I7: Да | J7: Да | K7: -623 | L7: 6987 | M7: 5187 | N7: =IF(K7<>"",K7+IF(L7<>"",L7,0)+IF(M7<>"",M7,0),"") | O7: =IF(N7<>"",N7+IF(O6<>"",O6,0),"") | P7: =IF(N7="","",IF(N7>0,"PROFIT","LOSS"))
A8: 5 | B8: 12.08.25 | C8: 307.4 | D8: 305 | E8: 295/305/310/320 | F8: 0.3 | G8: 0.345 | H8: 18 | I8: Да | J8: Да | K8: 335 | L8: 9330 | M8: 10658 | N8: =IF(K8<>"",K8+IF(L8<>"",L8,0)+IF(M8<>"",M8,0),"") | O8: =IF(N8<>"",N8+IF(O7<>"",O7,0),"") | P8: =IF(N8="","",IF(N8>0,"PROFIT","LOSS"))
A9: 6 | B9: 02.09.25 | C9: 308.4 | D9: 310 | E9: 300/310/315/325 | F9: 0.135 | G9: 0.155 | H9: 14 | I9: Да | J9: Да | K9: -7772 | L9: 955 | M9: 340 | N9: =IF(K9<>"",K9+IF(L9<>"",L9,0)+IF(M9<>"",M9,0),"") | O9: =IF(N9<>"",N9+IF(O8<>"",O8,0),"") | P9: =IF(N9="","",IF(N9>0,"PROFIT","LOSS"))
A10: 7 | B10: 07.10.25 | C10: 286.4 | D10: 285 | E10: 275/285/290/300 | F10: 0.178 | G10: 0.205 | H10: 10 | I10: Да | J10: Да | K10: 644 | L10: 5556 | M10: 4470 | N10: =IF(K10<>"",K10+IF(L10<>"",L10,0)+IF(M10<>"",M10,0),"") | O10: =IF(N10<>"",N10+IF(O9<>"",O9,0),"") | P10: =IF(N10="","",IF(N10>0,"PROFIT","LOSS"))
A11: 8 | B11: 11.11.25 | C11: 290.5 | D11: 290 | E11: 280/290/295/305 | F11: 0.412 | G11: 0.474 | H11: 15 | I11: Да | J11: Да | K11: 10844 | L11: 11632 | M11: 7738 | N11: =IF(K11<>"",K11+IF(L11<>"",L11,0)+IF(M11<>"",M11,0),"") | O11: =IF(N11<>"",N11+IF(O10<>"",O10,0),"") | P11: =IF(N11="","",IF(N11>0,"PROFIT","LOSS"))
A12: 9 | B12: 02.12.25 | C12: 299.5 | D12: 300 | E12: 290/300/305/315 | F12: 0.196 | G12: 0.225 | H12: 19 | I12: Да | J12: Да | K12: 1402 | L12: 2289 | M12: 3182 | N12: =IF(K12<>"",K12+IF(L12<>"",L12,0)+IF(M12<>"",M12,0),"") | O12: =IF(N12<>"",N12+IF(O11<>"",O11,0),"") | P12: =IF(N12="","",IF(N12>0,"PROFIT","LOSS"))
A13: 10 | B13: 13.01.26 | C13: 308.5 | D13: 310 | E13: 300/310/315/325 | F13: 0.144 | G13: 0.166 | H13: 20 | I13: Да | J13: Да | K13: 2747 | L13: 919 | M13: 1219 | N13: =IF(K13<>"",K13+IF(L13<>"",L13,0)+IF(M13<>"",M13,0),"") | O13: =IF(N13<>"",N13+IF(O12<>"",O12,0),"") | P13: =IF(N13="","",IF(N13>0,"PROFIT","LOSS"))
A14: 11 | B14: 17.02.26 | C14: 314 | D14: 315 | E14: 305/315/320/330 | F14: 0.106 | G14: 0.122 | H14: 21 | I14: Да | J14: Да | K14: 970 | L14: 1214 | M14: 3357 | N14: =IF(K14<>"",K14+IF(L14<>"",L14,0)+IF(M14<>"",M14,0),"") | O14: =IF(N14<>"",N14+IF(O13<>"",O13,0),"") | P14: =IF(N14="","",IF(N14>0,"PROFIT","LOSS"))
A15: 12 | N15: =IF(K15<>"",K15+IF(L15<>"",L15,0)+IF(M15<>"",M15,0),"") | O15: =IF(N15<>"",N15+IF(O14<>"",O14,0),"") | P15: =IF(N15="","",IF(N15>0,"PROFIT","LOSS"))
A16: 13 | N16: =IF(K16<>"",K16+IF(L16<>"",L16,0)+IF(M16<>"",M16,0),"") | O16: =IF(N16<>"",N16+IF(O15<>"",O15,0),"") | P16: =IF(N16="","",IF(N16>0,"PROFIT","LOSS"))
A17: 14 | N17: =IF(K17<>"",K17+IF(L17<>"",L17,0)+IF(M17<>"",M17,0),"") | O17: =IF(N17<>"",N17+IF(O16<>"",O16,0),"") | P17: =IF(N17="","",IF(N17>0,"PROFIT","LOSS"))
A18: 15 | N18: =IF(K18<>"",K18+IF(L18<>"",L18,0)+IF(M18<>"",M18,0),"") | O18: =IF(N18<>"",N18+IF(O17<>"",O17,0),"") | P18: =IF(N18="","",IF(N18>0,"PROFIT","LOSS"))
A19: 16 | N19: =IF(K19<>"",K19+IF(L19<>"",L19,0)+IF(M19<>"",M19,0),"") | O19: =IF(N19<>"",N19+IF(O18<>"",O18,0),"") | P19: =IF(N19="","",IF(N19>0,"PROFIT","LOSS"))
A20: 17 | N20: =IF(K20<>"",K20+IF(L20<>"",L20,0)+IF(M20<>"",M20,0),"") | O20: =IF(N20<>"",N20+IF(O19<>"",O19,0),"") | P20: =IF(N20="","",IF(N20>0,"PROFIT","LOSS"))
A21: 18 | N21: =IF(K21<>"",K21+IF(L21<>"",L21,0)+IF(M21<>"",M21,0),"") | O21: =IF(N21<>"",N21+IF(O20<>"",O20,0),"") | P21: =IF(N21="","",IF(N21>0,"PROFIT","LOSS"))
A22: 19 | N22: =IF(K22<>"",K22+IF(L22<>"",L22,0)+IF(M22<>"",M22,0),"") | O22: =IF(N22<>"",N22+IF(O21<>"",O21,0),"") | P22: =IF(N22="","",IF(N22>0,"PROFIT","LOSS"))
A23: 20 | N23: =IF(K23<>"",K23+IF(L23<>"",L23,0)+IF(M23<>"",M23,0),"") | O23: =IF(N23<>"",N23+IF(O22<>"",O22,0),"") | P23: =IF(N23="","",IF(N23>0,"PROFIT","LOSS"))
A24: 21 | N24: =IF(K24<>"",K24+IF(L24<>"",L24,0)+IF(M24<>"",M24,0),"") | O24: =IF(N24<>"",N24+IF(O23<>"",O23,0),"") | P24: =IF(N24="","",IF(N24>0,"PROFIT","LOSS"))
A26: СТАТИСТИКА
A27: Всего циклов: | B27: =COUNTA(N4:N24)
A28: Win rate: | B28: =IF(B27=0,"",COUNTIF(N4:N24,">0")/B27)
A29: Суммарный P&L: | B29: =IF(COUNTA(N4:N24)=0,"",SUM(N4:N24))
A30: Средний P&L/цикл: | B30: =IF(B27=0,"",AVERAGE(N4:N24))
A31: Max Drawdown: | B31: =IF(COUNTA(O4:O24)=0,"",MIN(O4:O24))
A32: Лучший цикл: | B32: =IF(COUNTA(N4:N24)=0,"",MAX(N4:N24))
A33: Худший цикл: | B33: =IF(COUNTA(N4:N24)=0,"",MIN(N4:N24))
A34: Profit Factor: | B34: =IF(SUMIF(N4:N24,"<0")=0,"INF",SUMIF(N4:N24,">0")/ABS(SUMIF(N4:N24,"<0")))

Sheet Decision Map
A1: КАРТА ПРИНЯТИЯ РЕШЕНИЙ — ГИБРИДНЫЙ КОНДОР v2
A2: Зелёный = ДА | Красный = НЕТ | Жёлтый = с условием
A4: ДЕЙСТВИЕ | B4: ФЛЭТ (R<6,Mom<3) | C4: БОКОВИК (R 6-10) | D4: ТРЕНД ВВЕРХ (Mom>6) | E4: ТРЕНД ВНИЗ (Mom<-6) | F4: ПОСЛЕ ШОКА | G4: ДО ЭКСПИР.<2д | H4: ПРИНЦИП
A5: ВХОД В КОНДОР | B5: YES | C5: 50% | D5: NO | E5: NO | F5: NO | G5: NO | H5: R<6, Mom<3
A6: ДЕРЖАТЬ ПОЗИЦИЮ | B6: YES | C6: YES | D6: WAIT | E6: WAIT | F6: YES | G6: WAIT | H6: Следи страйки
A7: ПРОДАТЬ BUY CALL | B7: YES 100% | C7: NO | D7: NO | E7: 50% | F7: NO | G7: NO | H7: Флэт д10+
A8: ROLL: откупить SELL CALL | B8: YES | C8: NO | D8: NO | E8: CAREFUL | F8: NO | G8: NO | H8: Покрыт акциями
A9: ROLL: продать ATM CALL | B9: YES | C9: NO | D9: NO | E9: NO | F9: NO | G9: NO | H9: Акции = покрытие
A10: ПРОДАТЬ 50% BUY PUT | B10: YES | C10: NO | D10: YES | E10: NO | F10: NO | G10: NO | H10: Не при тренде вниз
A11: ЗАКРЫТЬ SELL PUT | B11: NO | C11: NO | D11: NO | E11: 50% | F11: YES | G11: YES | H11: При угрозе страйка
A12: ПРОДАТЬ АКЦИИ | B12: NO | C12: NO | D12: NO | E12: NO | F12: NO | G12: NO | H12: Только нарушение страйка
A13: ЗАКРЫТЬ ВСЁ | B13: NO | C13: NO | D13: NO | E13: NO | F13: DECIDE | G13: YES | H13: P&L>70% или -2дня
A15: ЖЁСТКИЕ ЗАПРЕТЫ
A16: ❌ R > 12 руб → не торговать в этот день
A17: ❌ После падения > 10 руб → запрет SELL PUT следующие 2 дня
A18: ❌ После роста > 10 руб → запрет Roll ATM Call следующие 2 дня
A19: ❌ До/после новостей ЦБ или дивидендов → не активировать Фазу 2
A20: ❌ Roll: нет если до экспирации < 7 дней
A21: ❌ Roll: нет если SELL CALL вырос > 150% цены входа
A22: ❌ Никогда не продавать PUT при Momentum < -3 руб
A23: ❌ Никогда не продавать ATM Call без покрытия акциями
A25: ПРАВИЛА ВЫХОДА
A26: ✅ Прибыль >= 70% от макс. → немедленно закрыть все ноги
A27: ✅ За 2 торговых дня до экспирации → принудительный выход
... A29: ✅ Просадка P&L > 50% макс. убытка → пересмотр позиции
A31: ТЕКУЩАЯ СТАДИЯ | B31: =Dashbord!I16

Sheet Guide
A1: ИНСТРУКЦИЯ ПО ИСПОЛЬЗОВАНИЮ
A3: 🟢 ЧТО ВВОДИТЬ
A4: Ячейки с тёмно-ЗЕЛЁНЫМ фоном — вводить вручную. Остальное считается автоматически. Ячейки с синим/тёмным фоном — формулы, не трогать.
A6: 📊 ДАШБОРД
A7: Блок ТЕКУЩАЯ ПОЗИЦИЯ: заполни один раз при открытии — дату, цену S0, страйки, кол-во акций, дату экспирации. Блок РЫНОЧНЫЕ ДАННЫЕ: КАЖДЫЙ день вводи Close/High/Low/PrevClose/IV. Блок СИГНАЛ: автоматически покажет режим рынка и рекомендованные действия. Блок ФАЗА 2: подскажет, когда пора активировать Фазу 2.
A9: 📅 ЖУРНАЛ ДНЯ
A10: Добавляй новую строку каждый торговый день. Ввод: Дата, Close, High, Low, PrevClose, IV%. Авто: R, Momentum, Δ от центра, Режим (FLAT/TREND/WAIT), сигналы CALL/PUT, Фаза2. Колонка ФАЗА2: считает флэт-дни за последние 10 сессий. Когда >=8 → 'ACTIVATE'.
A12: 🧮 КАЛЬКУЛЯТОР (лист Calc_PnL)
A13: Введи S, страйки, σ (IV), дни до экспирации, размер лота. Авто-расчёт: цена каждой ноги по BS-формуле через NORM.S.DIST. Нетто дебет/кредит: итоговая стоимость входа. Таблица P&L: 50 точек, цветная шкала, встроенный график.
A15: 📋 ЖУРНАЛ ЦИКЛОВ (лист Cycles)
A16: После закрытия каждого 21-дневного цикла заполни строку. Ввод: дата входа, S0, центр, страйки, HV21, IV, кол-во флэт-дней, признаки Фазы2 и Roll, P&L компонентов. Авто: итоговый P&L, кумулятивный P&L, цветная метка PROFIT/LOSS, статистика, кумулятивный график.
A18: 🗺️ КАРТА РЕШЕНИЙ (лист Decision Map)
... A28: d1 = (LN(S/K) + 0.5*σ²*T) / (σ*√T) d2 = d1 - σ*√T Call = S*N(d1) - K*N(d2) Put = Call - S + K В листе Calc_PnL: σ вводить как IV (имплицитная), не HV21. T = кол-во дней до экспирации (не доля года).

Sheet VBA_Setup
A1: VBA code for Refresh Quotes button
A2: Sub RefreshQuotesAndCalc() Application.ScreenUpdating = False Application.EnableEvents = False ThisWorkbook.RefreshAll Application.CalculateFull MsgBox "Котировки и расчёты обновлены", vbInformation Application.EnableEvents = True Application.ScreenUpdating = True End Sub
A4: Как подключить кнопку:
A5: 1. Сохрани файл как .xlsm
A6: 2. Alt+F11 -> Insert -> Module -> вставь код из A2
A7: 3. Developer -> Insert -> Button -> назначь RefreshQuotesAndCalc
A8: 4. Data -> Refresh All тоже будет работать
A10: Если WEBSERVICE/FILTERXML не работают в локали, используй ручной ввод.
